{
  "brands": {
    "BENTNER": "BT",
    "BIG GASTINO": "BG",
    "BLACK OUT": "BO",
    "BRANGO": "BR",
    "BREAD BUTTONS": "BB",
    "BUFFON": "BF",
    "COONLESS": "CL",
    "DIESEL": "D",
    "DYNAMO": "DY",
    "EL FAGO": "EF",
    "EMPO": "EM",
    "ENJOY": "EN",
    "FIGO": "FI",
    "FIXMAN": "FX",
    "GUARD": "GU",
    "Gabbia": "GA",
    "JONNY WOLF": "JW",
    "JR": "JR",
    "KEPS": "KE",
    "KOMBLEN": "KO",
    "LENNASO": "LN",
    "MARCAO": "MC",
    "MARKOVA": "MA",
    "MARSHAL": "MT",
    "MC": "MCC",
    "POLIMPIER": "PP",
    "POLO": "PO",
    "RAUS": "RA",
    "RCJ": "RCJ",
    "RUGATCHI": "RU",
    "SAVAGE": "SA",
    "SENTEZ": "SZ",
    "TMK": "TMK",
    "TWENHIL": "TW",
    "Tommy Hilfiger": "TH",
    "WARREN WEBBER": "WW",
    "X2DENIM": "X2",
    "YES DESIGN": "YD",
    "YTWO": "YT",
    "GREENWEST": "GW",
    "WELLALUX": "WL",
    "BLACKZI": "BZ",
    "AGRESIF": "AG",
    "POLOROMANO": "PR"
  },
  "_comment": "Map each supplier/brand to a single-letter code. The code is used in product display names like 'Jeans - #D001'. Customers see the code but cannot trace it back to the brand. Add new brands here as needed."
}